Workbook

Sheet Inputs
A1: Inputs
A2: Monthly model, January 2026 to December 2028.
A3: Starting MRR | B3: 185000 | C3: USD, January 2026
A4: Growth | B4: 0.04
A5: Monthly churn | B5: 0.015 | C5: share of beginning MRR lost each month
A6: ARPA per month | B6: 650 | C6: USD per customer
A7: CAC per new customer | B7: 5200 | C7: USD
A8: COGS % of revenue | B8: 0.22
A9: Fixed G&A per month | B9: 38000 | C9: USD
A10: D&A per month | B10: 9000 | C10: USD
A11: Capex per month | B11: 12000 | C11: USD
A12: Tax rate | B12: 0.21
A13: AR (months of revenue) | B13: 1 | C13: net 30 terms
A14: AP (share of monthly costs) | B14: 0.5
A16: Opening balance sheet
A17: Opening cash | B17: 6200000 | C17: Dec 31, 2025
A18: Opening AR | B18: 181500
A19: Opening PP&E, net | B19: 310000
A20: Opening AP | B20: 98000
A21: Opening paid-in capital | B21: 9500000
A22: Opening retained earnings | B22: =B17+B18+B19-B20-B21 -> -2906500 | C22: balancing figure
A24: Loaded cost per head, per month
A25: Engineering | B25: 13750 | C25: loaded cost per head per month
A26: Sales | B26: 10000 | C26: loaded cost per head per month
A27: G&A | B27: 9200 | C27: loaded cost per head per month
A29: Headcount plan | B29: 46023 | C29: 46054 | D29: 46082 | E29: 46113 | F29: 46143 | G29: 46174 | H29: 46204 | I29: 46235 | J29: 46266 | K29: 46296 | L29: 46327 | M29: 46357 | N29: 46388 | O29: 46419 | P29: 46447 | Q29: 46478 | R29: 46508 | S29: 46539 | T29: 46569 | U29: 46600 | V29: 46631 | W29: 46661 | X29: 46692 | Y29: 46722 | Z29: 46753 | AA29: 46784 | AB29: 46813 | AC29: 46844 | AD29: 46874 | AE29: 46905 | AF29: 46935 | AG29: 46966 | AH29: 46997 | AI29: 47027 | AJ29: 47058 | AK29: 47088
A30: Engineering | B30: 18 | C30: 18 | D30: 19 | E30: 19 | F30: 20 | G30: 20 | H30: 21 | I30: 21 | J30: 22 | K30: 22 | L30: 23 | M30: 23 | N30: 23 | O30: 24 | P30: 24 | Q30: 25 | R30: 25 | S30: 26 | T30: 26 | U30: 27 | V30: 27 | W30: 28 | X30: 28 | Y30: 29 | Z30: 29 | AA30: 29 | AB30: 30 | AC30: 30 | AD30: 31 | AE30: 31 | AF30: 32 | AG30: 32 | AH30: 33 | AI30: 33 | AJ30: 34 | AK30: 34
A31: Sales | B31: 8 | C31: 8 | D31: 9 | E31: 9 | F31: 9 | G31: 10 | H31: 10 | I31: 10 | J31: 11 | K31: 11 | L31: 11 | M31: 12 | N31: 12 | O31: 12 | P31: 13 | Q31: 13 | R31: 13 | S31: 14 | T31: 14 | U31: 15 | V31: 15 | W31: 15 | X31: 16 | Y31: 16 | Z31: 16 | AA31: 17 | AB31: 17 | AC31: 17 | AD31: 18 | AE31: 18 | AF31: 18 | AG31: 19 | AH31: 19 | AI31: 19 | AJ31: 20 | AK31: 20
A32: G&A | B32: 5 | C32: 5 | D32: 5 | E32: 5 | F32: 5 | G32: 6 | H32: 6 | I32: 6 | J32: 6 | K32: 6 | L32: 6 | M32: 6 | N32: 6 | O32: 6 | P32: 7 | Q32: 7 | R32: 7 | S32: 7 | T32: 7 | U32: 7 | V32: 7 | W32: 7 | X32: 8 | Y32: 8 | Z32: 8 | AA32: 8 | AB32: 8 | AC32: 8 | AD32: 8 | AE32: 8 | AF32: 8 | AG32: 9 | AH32: 9 | AI32: 9 | AJ32: 9 | AK32: 9

Sheet Revenue
A1: Revenue build (USD)
A2: Month | B2: 46023 | C2: 46054 | D2: 46082 | E2: 46113 | F2: 46143 | G2: 46174 | H2: 46204 | I2: 46235 | J2: 46266 | K2: 46296 | L2: 46327 | M2: 46357 | N2: 46388 | O2: 46419 | P2: 46447 | Q2: 46478 | R2: 46508 | S2: 46539 | T2: 46569 | U2: 46600 | V2: 46631 | W2: 46661 | X2: 46692 | Y2: 46722 | Z2: 46753 | AA2: 46784 | AB2: 46813 | AC2: 46844 | AD2: 46874 | AE2: 46905 | AF2: 46935 | AG2: 46966 | AH2: 46997 | AI2: 47027 | AJ2: 47058 | AK2: 47088
A4: Beginning MRR | B4: 185000 | C4: 188399 | D4: 194039 | E4: 199404 | F4: 202957 | G4: 209464 | H4: 216022 | I4: 220699 | J4: =I7 -> 226872 | K4: =J7 -> 232543.8 | L4: =K7 -> 238357.4 | M4: =L7 -> 244316.33 | N4: =M7 -> 250424.24 | O4: =N7 -> 256684.84 | P4: =O7 -> 263101.97 | Q4: =P7 -> 269679.51 | ... AK4: =AJ7 -> 431123.21
A5: New MRR | B5: 6457 | C5: 8388 | D5: 8018 | E5: 7108 | F5: 8771 | G5: 9096 | H5: 7370 | I5: 8874 | J5: =J4*Inputs!$B$4 -> 9074.88 | K5: =K4*Inputs!$B$4 -> 9301.752 | L5: =L4*Inputs!$B$4 -> 9534.2958 | M5: =M4*Inputs!$B$4 -> 9772.6532 | N5: =N4*Inputs!$B$4 -> 10016.97 | O5: =O4*Inputs!$B$4 -> 10267.394 | P5: =P4*Inputs!$B$4 -> 10524.079 | Q5: =Q4*Inputs!$B$4 -> 10787.181 | ... W5: =W4*Inputs!$B$4 -> 12509.822 | X5: =X4*Inputs!$B$5 -> 4808.463 | Y5: =Y4*Inputs!$B$4 -> 12822.568 | Z5: =Z4*Inputs!$B$4 -> 13143.132 | AA5: =AA4*Inputs!$B$4 -> 13471.71 | AB5: =AB4*Inputs!$B$4 -> 13808.503 | AC5: =AC4*Inputs!$B$4 -> 14153.716 | AD5: =AD4*Inputs!$B$4 -> 14507.559 | AE5: =AE4*Inputs!$B$4 -> 14870.248 | AF5: =AF4*Inputs!$B$4 -> 15242.004 | ... AK5: =AK4*Inputs!$B$4 -> 17244.928
A6: Churned MRR | B6: 3058 | C6: 2748 | D6: 2653 | E6: 3555 | F6: 2264 | G6: 2538 | H6: 2693 | I6: 2701 | J6: =J4*Inputs!$B$5 -> 3403.08 | K6: =K4*Inputs!$B$5 -> 3488.157 | L6: =L4*Inputs!$B$5 -> 3575.3609 | M6: =M4*Inputs!$B$5 -> 3664.7449 | N6: =N4*Inputs!$B$5 -> 3756.3636 | O6: =O4*Inputs!$B$5 -> 3850.2727 | P6: =P4*Inputs!$B$5 -> 3946.5295 | Q6: =Q4*Inputs!$B$5 -> 4045.1927 | ... AK6: =AK4*Inputs!$B$5 -> 6466.8481
A7: Ending MRR | B7: =B4+B5-B6 -> 188399 | C7: =C4+C5-C6 -> 194039 | D7: =D4+D5-D6 -> 199404 | E7: =E4+E5-E6 -> 202957 | F7: =F4+F5-F6 -> 209464 | G7: =G4+G5-G6 -> 216022 | H7: =H4+H5-H6 -> 220699 | I7: =I4+I5-I6 -> 226872 | ... AK7: =AK4+AK5-AK6 -> 441901.29
A8: New customers | B8: 10 | C8: 13 | D8: 12 | E8: 11 | F8: 13 | G8: 14 | H8: 11 | I8: 14 | J8: =J5/Inputs!$B$6 -> 13.961354 | K8: =K5/Inputs!$B$6 -> 14.310388 | L8: =L5/Inputs!$B$6 -> 14.668147 | M8: =M5/Inputs!$B$6 -> 15.034851 | N8: =N5/Inputs!$B$6 -> 15.410722 | O8: =O5/Inputs!$B$6 -> 15.79599 | P8: =P5/Inputs!$B$6 -> 16.19089 | Q8: =Q5/Inputs!$B$6 -> 16.595662 | ... AK8: =AK5/Inputs!$B$6 -> 26.530659

Sheet P&L
A1: P&L (USD)
A2: Month | B2: 46023 | C2: 46054 | D2: 46082 | E2: 46113 | F2: 46143 | G2: 46174 | H2: 46204 | I2: 46235 | J2: 46266 | K2: 46296 | L2: 46327 | M2: 46357 | N2: 46388 | O2: 46419 | P2: 46447 | Q2: 46478 | R2: 46508 | S2: 46539 | T2: 46569 | U2: 46600 | V2: 46631 | W2: 46661 | X2: 46692 | Y2: 46722 | Z2: 46753 | AA2: 46784 | AB2: 46813 | AC2: 46844 | AD2: 46874 | AE2: 46905 | AF2: 46935 | AG2: 46966 | AH2: 46997 | AI2: 47027 | AJ2: 47058 | AK2: 47088
A4: Revenue | B4: 191756 | C4: 196164 | D4: 198653 | E4: 206350 | F4: 210722 | G4: 218234 | H4: 220543 | I4: 225613 | J4: =Revenue!J7 -> 232543.8 | K4: =Revenue!K7 -> 238357.4 | L4: =Revenue!L7 -> 244316.33 | M4: =Revenue!M7 -> 250424.24 | N4: =Revenue!N7*1.07 -> 274652.78 | O4: =Revenue!O7 -> 263101.97 | P4: =Revenue!P7 -> 269679.51 | Q4: =Revenue!Q7 -> 276421.5 | R4: =Revenue!R7 -> 283332.04 | S4: =Revenue!S7 -> 290415.34 | T4: =Revenue!T7 -> 297675.72 | U4: =Revenue!U7 -> 305117.62 | V4: =Revenue!V7 -> 312745.56 | ... AK4: =Revenue!AK7 -> 441901.29
A5: COGS | B5: 45184 | C5: 45327 | D5: 46649 | E5: 47125 | F5: 45960 | G5: 50431 | H5: 49609 | I5: 50163 | J5: =J4*Inputs!$B$8 -> 51159.636 | K5: =K4*Inputs!$B$8 -> 52438.627 | L5: =L4*Inputs!$B$8 -> 53749.593 | M5: =M4*Inputs!$B$8 -> 55093.332 | N5: =N4*Inputs!$B$8 -> 60423.612 | O5: =O4*Inputs!$B$8 -> 57882.432 | P5: =P4*Inputs!$B$8 -> 59329.493 | Q5: =Q4*Inputs!$B$8 -> 60812.73 | ... AK5: =AK4*Inputs!$B$8 -> 97218.283
A6: Gross Profit | B6: =B4-B5 -> 146572 | C6: =C4-C5 -> 150837 | D6: =D4-D5 -> 152004 | E6: =E4-E5 -> 159225 | F6: =F4-F5 -> 164762 | G6: =G4-G5 -> 167803 | H6: =H4-H5 -> 170934 | I6: =I4-I5 -> 175450 | ... AK6: =AK4-AK5 -> 344683
A7: Sales & Marketing | B7: 132352 | C7: 143938 | D7: 159805 | E7: 146220 | F7: 152329 | G7: 184991 | H7: 164486 | I7: 169501 | J7: =Revenue!J8*Inputs!$B$7+Inputs!J31*Inputs!$B$26 -> 182599.04 | K7: =Revenue!K8*Inputs!$B$7+Inputs!K31*Inputs!$B$26 -> 184414.02 | L7: =Revenue!L8*Inputs!$B$7+Inputs!L31*Inputs!$B$26 -> 186274.37 | M7: =Revenue!M8*Inputs!$B$7+Inputs!M31*Inputs!$B$26 -> 198181.23 | N7: =Revenue!N8*Inputs!$B$7+Inputs!N31*Inputs!$B$26 -> 200135.76 | O7: =Revenue!O8*Inputs!$B$7+Inputs!O31*Inputs!$B$26 -> 202139.15 | P7: =Revenue!P8*Inputs!$B$7+Inputs!P31*Inputs!$B$26 -> 214192.63 | Q7: =Revenue!Q8*Inputs!$B$7+Inputs!Q31*Inputs!$B$26 -> 216297.44 | ... AK7: =Revenue!AK8*Inputs!$B$7+Inputs!AK31*Inputs!$B$26 -> 337959.43
A8: R&D | B8: 243207 | C8: 254427 | D8: 268537 | E8: 262563 | F8: 282473 | G8: 271772 | H8: 280503 | I8: 296530 | J8: =Inputs!J30*Inputs!$B$25 -> 302500 | K8: =Inputs!K30*Inputs!$B$25 -> 302500 | L8: =Inputs!L30*Inputs!$B$25 -> 316250 | M8: =Inputs!M30*Inputs!$B$25 -> 316250 | N8: =Inputs!N30*Inputs!$B$25 -> 316250 | O8: =Inputs!O30*Inputs!$B$25 -> 330000 | P8: =Inputs!P30*Inputs!$B$25 -> 330000 | Q8: =Inputs!Q30*Inputs!$B$25 -> 343750 | ... AK8: =Inputs!AK30*Inputs!$B$25 -> 467500
A9: G&A | B9: 80387 | C9: 89891 | D9: 82653 | E9: 86168 | F9: 85811 | G9: 98921 | H9: 89608 | I9: 95530 | J9: =Inputs!J32*Inputs!$B$27+Inputs!$B$9 -> 93200 | K9: =Inputs!K32*Inputs!$B$27+Inputs!$B$9 -> 93200 | L9: =Inputs!L32*Inputs!$B$27+Inputs!$B$9 -> 93200 | M9: =Inputs!M32*Inputs!$B$27+Inputs!$B$9 -> 93200 | N9: =Inputs!N32*Inputs!$B$27+Inputs!$B$9 -> 93200 | O9: =Inputs!O32*Inputs!$B$27+Inputs!$B$9 -> 93200 | P9: =Inputs!P32*Inputs!$B$27+Inputs!$B$9 -> 102400 | Q9: =Inputs!Q32*Inputs!$B$27+Inputs!$B$9 -> 102400 | ... AA9: =Inputs!AA32*Inputs!$B$27+Inputs!$B$9 -> 111600 | AB9: =Inputs!AB32*Inputs!$B$27 -> 73600 | AC9: =Inputs!AC32*Inputs!$B$27+Inputs!$B$9 -> 111600 | AD9: =Inputs!AD32*Inputs!$B$27+Inputs!$B$9 -> 111600 | AE9: =Inputs!AE32*Inputs!$B$27+Inputs!$B$9 -> 111600 | AF9: =Inputs!AF32*Inputs!$B$27+Inputs!$B$9 -> 111600 | AG9: =Inputs!AG32*Inputs!$B$27+Inputs!$B$9 -> 120800 | AH9: =Inputs!AH32*Inputs!$B$27+Inputs!$B$9 -> 120800 | AI9: =Inputs!AI32*Inputs!$B$27+Inputs!$B$9 -> 120800 | AJ9: =Inputs!AJ32*Inputs!$B$27+Inputs!$B$9 -> 120800 | AK9: =Inputs!AK32*Inputs!$B$27+Inputs!$B$9 -> 120800
A10: Total OpEx | B10: =SUM(B7:B9) -> 455946 | C10: =SUM(C7:C9) -> 488256 | D10: =SUM(D7:D9) -> 510995 | E10: =SUM(E7:E9) -> 494951 | F10: =SUM(F7:F9) -> 520613 | G10: =SUM(G7:G9) -> 555684 | H10: =SUM(H7:H9) -> 534597 | I10: =SUM(I7:I9) -> 561561 | ... AK10: =SUM(AK7:AK9) -> 926259.43
A11: EBITDA | B11: =B6-B10 -> -309374 | C11: =C6-C10 -> -337419 | D11: =D6-D10 -> -358991 | E11: =E6-E10 -> -335726 | F11: =F6-F10 -> -355851 | G11: =G6-G10 -> -387881 | H11: =H6-H10 -> -363663 | I11: =I6-I10 -> -386111 | ... AK11: =AK6-AK10 -> -581576.42
A12: D&A | B12: 9000 | C12: 9000 | D12: 9000 | E12: 9000 | F12: 9000 | G12: 9000 | H12: 9000 | I12: 9000 | J12: =Inputs!$B$10 -> 9000 | K12: =Inputs!$B$10 -> 9000 | L12: =Inputs!$B$10 -> 9000 | M12: =Inputs!$B$10 -> 9000 | N12: =Inputs!$B$10 -> 9000 | O12: =Inputs!$B$10 -> 9000 | P12: =Inputs!$B$10 -> 9000 | Q12: =Inputs!$B$10 -> 9000 | ... AK12: =Inputs!$B$10 -> 9000
A13: EBIT | B13: =B11-B12 -> -318374 | C13: =C11-C12 -> -346419 | D13: =D11-D12 -> -367991 | E13: =E11-E12 -> -344726 | F13: =F11-F12 -> -364851 | G13: =G11-G12 -> -396881 | H13: =H11-H12 -> -372663 | I13: =I11-I12 -> -395111 | ... AK13: =AK11-AK12 -> -590576.42
A14: Taxes | B14: 0 | C14: 0 | D14: 0 | E14: 0 | F14: 0 | G14: 0 | H14: 0 | I14: 0 | J14: =MAX(0,J13)*Inputs!$B$12 -> 0 | K14: =MAX(0,K13)*Inputs!$B$12 -> 0 | L14: =MAX(0,L13)*Inputs!$B$12 -> 0 | M14: =MAX(0,M13)*Inputs!$B$12 -> 0 | N14: =MAX(0,N13)*Inputs!$B$12 -> 0 | O14: =MAX(0,O13)*Inputs!$B$12 -> 0 | P14: =MAX(0,P13)*Inputs!$B$12 -> 0 | Q14: =MAX(0,Q13)*Inputs!$B$12 -> 0 | ... AK14: =MAX(0,AK13)*Inputs!$B$12 -> 0
A15: Net Income | B15: =B13-B14 -> -318374 | C15: =C13-C14 -> -346419 | D15: =D13-D14 -> -367991 | E15: =E13-E14 -> -344726 | F15: =F13-F14 -> -364851 | G15: =G13-G14 -> -396881 | H15: =H13-H14 -> -372663 | I15: =I13-I14 -> -395111 | ... AK15: =AK13-AK14 -> -590576.42

Sheet Cash Flow
A1: Cash Flow (USD)
A2: Month | B2: 46023 | C2: 46054 | D2: 46082 | E2: 46113 | F2: 46143 | G2: 46174 | H2: 46204 | I2: 46235 | J2: 46266 | K2: 46296 | L2: 46327 | M2: 46357 | N2: 46388 | O2: 46419 | P2: 46447 | Q2: 46478 | R2: 46508 | S2: 46539 | T2: 46569 | U2: 46600 | V2: 46631 | W2: 46661 | X2: 46692 | Y2: 46722 | Z2: 46753 | AA2: 46784 | AB2: 46813 | AC2: 46844 | AD2: 46874 | AE2: 46905 | AF2: 46935 | AG2: 46966 | AH2: 46997 | AI2: 47027 | AJ2: 47058 | AK2: 47088
A4: Net Income | B4: ='P&L'!B15 -> -318374 | C4: ='P&L'!C15 -> -346419 | D4: ='P&L'!D15 -> -367991 | E4: ='P&L'!E15 -> -344726 | F4: ='P&L'!F15 -> -364851 | G4: ='P&L'!G15 -> -396881 | H4: ='P&L'!H15 -> -372663 | I4: ='P&L'!I15 -> -395111 | ... AK4: ='P&L'!AK15 -> -590576.42
A5: D&A | B5: ='P&L'!B12 -> 9000 | C5: ='P&L'!C12 -> 9000 | D5: ='P&L'!D12 -> 9000 | E5: ='P&L'!E12 -> 9000 | F5: ='P&L'!F12 -> 9000 | G5: ='P&L'!G12 -> 9000 | H5: ='P&L'!H12 -> 9000 | I5: ='P&L'!I12 -> 9000 | ... AK5: ='P&L'!AK12 -> 9000
A6: Change in AR | B6: =-('Balance Sheet'!B5-Inputs!$B$18) -> -10256 | C6: =-('Balance Sheet'!C5-'Balance Sheet'!B5) -> -4408 | D6: =-('Balance Sheet'!D5-'Balance Sheet'!C5) -> -2489 | E6: =-('Balance Sheet'!E5-'Balance Sheet'!D5) -> -7697 | F6: =-('Balance Sheet'!F5-'Balance Sheet'!E5) -> -4372 | G6: =-('Balance Sheet'!G5-'Balance Sheet'!F5) -> -7512 | H6: =-('Balance Sheet'!H5-'Balance Sheet'!G5) -> -2309 | I6: =-('Balance Sheet'!I5-'Balance Sheet'!H5) -> -5070 | J6: =-('Balance Sheet'!J5-'Balance Sheet'!I5) -> -6930.8 | ... AK6: =-('Balance Sheet'!AK5-'Balance Sheet'!AJ5) -> -10778.08
A7: Change in AP | B7: ='Balance Sheet'!B9-Inputs!$B$20 -> 152565 | C7: ='Balance Sheet'!C9-'Balance Sheet'!B9 -> 16226.5 | D7: ='Balance Sheet'!D9-'Balance Sheet'!C9 -> 12030.5 | E7: ='Balance Sheet'!E9-'Balance Sheet'!D9 -> -7784 | F7: ='Balance Sheet'!F9-'Balance Sheet'!E9 -> 12248.5 | G7: ='Balance Sheet'!G9-'Balance Sheet'!F9 -> 19771 | H7: ='Balance Sheet'!H9-'Balance Sheet'!G9 -> -10954.5 | I7: ='Balance Sheet'!I9-'Balance Sheet'!H9 -> 13759 | J7: ='Balance Sheet'!J9-'Balance Sheet'!I9 -> 8867.338 | ... AK7: ='Balance Sheet'!AK9-'Balance Sheet'!AJ9 -> 2868.0208
A8: Cash from Operations | B8: =SUM(B4:B7) -> -167065 | C8: =SUM(C4:C7) -> -325600.5 | D8: =SUM(D4:D7) -> -349449.5 | E8: =SUM(E4:E7) -> -351207 | F8: =SUM(F4:F7) -> -347974.5 | G8: =SUM(G4:G7) -> -375622 | H8: =SUM(H4:H7) -> -376926.5 | I8: =SUM(I4:I7) -> -377422 | ... AK8: =SUM(AK4:AK7) -> -589486.48
A9: Capex | B9: =-Inputs!$B$11 -> -12000 | C9: =-Inputs!$B$11 -> -12000 | D9: =-Inputs!$B$11 -> -12000 | E9: =-Inputs!$B$11 -> -12000 | F9: =-Inputs!$B$11 -> -12000 | G9: =-Inputs!$B$11 -> -12000 | H9: =-Inputs!$B$11 -> -12000 | I9: =-Inputs!$B$11 -> -12000 | ... AK9: =-Inputs!$B$11 -> -12000
A10: Cash from Investing | B10: =B9 -> -12000 | C10: =C9 -> -12000 | D10: =D9 -> -12000 | E10: =E9 -> -12000 | F10: =F9 -> -12000 | G10: =G9 -> -12000 | H10: =H9 -> -12000 | I10: =I9 -> -12000 | ... AK10: =AK9 -> -12000
A11: Equity raised | B11: 0 | C11: 0 | D11: 0 | E11: 0 | F11: 0 | G11: 0 | H11: 0 | I11: 0 | J11: 0 | K11: 0 | L11: 0 | M11: 0 | N11: 0 | O11: 0 | P11: 15000000 | Q11: 0 | R11: 0 | S11: 0 | T11: 0 | U11: 0 | V11: 0 | W11: 0 | X11: 0 | Y11: 0 | Z11: 0 | AA11: 0 | AB11: 0 | AC11: 0 | AD11: 0 | AE11: 0 | AF11: 0 | AG11: 0 | AH11: 0 | AI11: 0 | AJ11: 0 | AK11: 0
A12: Cash from Financing | B12: =B11 -> 0 | C12: =C11 -> 0 | D12: =D11 -> 0 | E12: =E11 -> 0 | F12: =F11 -> 0 | G12: =G11 -> 0 | H12: =H11 -> 0 | I12: =I11 -> 0 | ... AK12: =AK11 -> 0
A13: Net Change in Cash | B13: =B8+B10+B12 -> -179065 | C13: =C8+C10+C12 -> -337600.5 | D13: =D8+D10+D12 -> -361449.5 | E13: =E8+E10+E12 -> -363207 | F13: =F8+F10+F12 -> -359974.5 | G13: =G8+G10+G12 -> -387622 | H13: =H8+H10+H12 -> -388926.5 | I13: =I8+I10+I12 -> -389422 | ... AK13: =AK8+AK10+AK12 -> -601486.48
A14: Beginning Cash | B14: =Inputs!$B$17 -> 6200000 | C14: =B15 -> 6020935 | D14: =C15 -> 5683334.5 | E14: =D15 -> 5321885 | F14: =E15 -> 4958678 | G14: =F15 -> 4598703.5 | H14: =G15 -> 4211081.5 | I14: =H15 -> 3822155 | J14: =I15 -> 3432733 | ... AK14: =AJ15 -> 5053857.1
A15: Ending Cash | B15: =B14+B13 -> 6020935 | C15: =C14+C13 -> 5683334.5 | D15: =D14+D13 -> 5321885 | E15: =E14+E13 -> 4958678 | F15: =F14+F13 -> 4598703.5 | G15: =G14+G13 -> 4211081.5 | H15: =H14+H13 -> 3822155 | I15: =I14+I13 -> 3432733 | ... AK15: =AK14+AK13 -> 4452370.6

Sheet Balance Sheet
A1: Balance Sheet (USD)
A2: Month | B2: 46023 | C2: 46054 | D2: 46082 | E2: 46113 | F2: 46143 | G2: 46174 | H2: 46204 | I2: 46235 | J2: 46266 | K2: 46296 | L2: 46327 | M2: 46357 | N2: 46388 | O2: 46419 | P2: 46447 | Q2: 46478 | R2: 46508 | S2: 46539 | T2: 46569 | U2: 46600 | V2: 46631 | W2: 46661 | X2: 46692 | Y2: 46722 | Z2: 46753 | AA2: 46784 | AB2: 46813 | AC2: 46844 | AD2: 46874 | AE2: 46905 | AF2: 46935 | AG2: 46966 | AH2: 46997 | AI2: 47027 | AJ2: 47058 | AK2: 47088
A4: Cash | B4: ='Cash Flow'!B15 -> 6020935 | C4: ='Cash Flow'!C15 -> 5683334.5 | D4: ='Cash Flow'!D15 -> 5321885 | E4: ='Cash Flow'!E15 -> 4958678 | F4: ='Cash Flow'!F15 -> 4598703.5 | G4: ='Cash Flow'!G15 -> 4211081.5 | H4: ='Cash Flow'!H15 -> 3822155 | I4: ='Cash Flow'!I15 -> 3432733 | ... Q4: ='Cash Flow'!Q15 -> 15034567 | R4: 14600000 | S4: ='Cash Flow'!S15 -> 14104524 | T4: ='Cash Flow'!T15 -> 13626549 | U4: ='Cash Flow'!U15 -> 13140048 | V4: ='Cash Flow'!V15 -> 12645104 | W4: ='Cash Flow'!W15 -> 12146802 | X4: ='Cash Flow'!X15 -> 11668569 | Y4: ='Cash Flow'!Y15 -> 11171729 | Z4: ='Cash Flow'!Z15 -> 10640903 | ... AK4: ='Cash Flow'!AK15 -> 4452370.6
A5: Accounts Receivable | B5: ='P&L'!B4*Inputs!$B$13 -> 191756 | C5: ='P&L'!C4*Inputs!$B$13 -> 196164 | D5: ='P&L'!D4*Inputs!$B$13 -> 198653 | E5: ='P&L'!E4*Inputs!$B$13 -> 206350 | F5: ='P&L'!F4*Inputs!$B$13 -> 210722 | G5: ='P&L'!G4*Inputs!$B$13 -> 218234 | H5: ='P&L'!H4*Inputs!$B$13 -> 220543 | I5: ='P&L'!I4*Inputs!$B$13 -> 225613 | ... AE5: ='P&L'!AE4*Inputs!$B$13 -> 381050.09 | AF5: ='P&L'!AE4*Inputs!$B$13 -> 381050.09 | AG5: ='P&L'!AG4*Inputs!$B$13 -> 400340.75 | AH5: ='P&L'!AH4*Inputs!$B$13 -> 410349.27 | AI5: ='P&L'!AI4*Inputs!$B$13 -> 420608.01 | AJ5: ='P&L'!AJ4*Inputs!$B$13 -> 431123.21 | AK5: ='P&L'!AK4*Inputs!$B$13 -> 441901.29
A6: PP&E, net | B6: =Inputs!$B$19+Inputs!$B$11-'P&L'!B12 -> 313000 | C6: =B6+Inputs!$B$11-'P&L'!C12 -> 316000 | D6: =C6+Inputs!$B$11-'P&L'!D12 -> 319000 | E6: =D6+Inputs!$B$11-'P&L'!E12 -> 322000 | F6: =E6+Inputs!$B$11-'P&L'!F12 -> 325000 | G6: =F6+Inputs!$B$11-'P&L'!G12 -> 328000 | H6: =G6+Inputs!$B$11-'P&L'!H12 -> 331000 | I6: =H6+Inputs!$B$11-'P&L'!I12 -> 334000 | J6: =I6+Inputs!$B$11-'P&L'!J12 -> 337000 | ... AK6: =AJ6+Inputs!$B$11-'P&L'!AK12 -> 418000
A7: Total Assets | B7: =SUM(B4:B6) -> 6525691 | C7: =SUM(C4:C6) -> 6195498.5 | D7: =SUM(D4:D6) -> 5839538 | E7: =SUM(E4:E6) -> 5487028 | F7: =SUM(F4:F6) -> 5134425.5 | G7: =SUM(G4:G6) -> 4757315.5 | H7: =SUM(H4:H6) -> 4373698 | I7: =SUM(I4:I6) -> 3992346 | ... AK7: =SUM(AK4:AK6) -> 5312271.9
A9: Accounts Payable | B9: =('P&L'!B5+'P&L'!B10)*Inputs!$B$14 -> 250565 | C9: =('P&L'!C5+'P&L'!C10)*Inputs!$B$14 -> 266791.5 | D9: =('P&L'!D5+'P&L'!D10)*Inputs!$B$14 -> 278822 | E9: =('P&L'!E5+'P&L'!E10)*Inputs!$B$14 -> 271038 | F9: =('P&L'!F5+'P&L'!F10)*Inputs!$B$14 -> 283286.5 | G9: =('P&L'!G5+'P&L'!G10)*Inputs!$B$14 -> 303057.5 | H9: =('P&L'!H5+'P&L'!H10)*Inputs!$B$14 -> 292103 | I9: =('P&L'!I5+'P&L'!I10)*Inputs!$B$14 -> 305862 | ... AK9: =('P&L'!AK5+'P&L'!AK10)*Inputs!$B$14 -> 511738.85
A10: Total Liabilities | B10: =B9 -> 250565 | C10: =C9 -> 266791.5 | D10: =D9 -> 278822 | E10: =E9 -> 271038 | F10: =F9 -> 283286.5 | G10: =G9 -> 303057.5 | H10: =H9 -> 292103 | I10: =I9 -> 305862 | ... AK10: =AK9 -> 511738.85
A12: Paid-in Capital | B12: =Inputs!$B$21+'Cash Flow'!B11 -> 9500000 | C12: =B12+'Cash Flow'!C11 -> 9500000 | D12: =C12+'Cash Flow'!D11 -> 9500000 | E12: =D12+'Cash Flow'!E11 -> 9500000 | F12: =E12+'Cash Flow'!F11 -> 9500000 | G12: =F12+'Cash Flow'!G11 -> 9500000 | H12: =G12+'Cash Flow'!H11 -> 9500000 | I12: =H12+'Cash Flow'!I11 -> 9500000 | J12: =I12+'Cash Flow'!J11 -> 9500000 | ... AK12: =AJ12+'Cash Flow'!AK11 -> 24500000
A13: Retained Earnings | B13: =Inputs!$B$22+'P&L'!B15 -> -3224874 | C13: =B13+'P&L'!C15 -> -3571293 | D13: =C13+'P&L'!D15 -> -3939284 | E13: =D13+'P&L'!E15 -> -4284010 | F13: =E13+'P&L'!F15 -> -4648861 | G13: =F13+'P&L'!G15 -> -5045742 | H13: =G13+'P&L'!H15 -> -5418405 | I13: =H13+'P&L'!I15 -> -5813516 | J13: =I13+'P&L'!J15 -> -6219430.9 | ... AK13: =AJ13+'P&L'!AK15 -> -19699467
A14: Total Equity | B14: =B12+B13 -> 6275126 | C14: =C12+C13 -> 5928707 | D14: =D12+D13 -> 5560716 | E14: =E12+E13 -> 5215990 | F14: =F12+F13 -> 4851139 | G14: =G12+G13 -> 4454258 | H14: =H12+H13 -> 4081595 | I14: =I12+I13 -> 3686484 | ... AK14: =AK12+AK13 -> 4800533.1
A16: Total Liabilities & Equity | B16: =B10+B14 -> 6525691 | C16: =C10+C14 -> 6195498.5 | D16: =D10+D14 -> 5839538 | E16: =E10+E14 -> 5487028 | F16: =F10+F14 -> 5134425.5 | G16: =G10+G14 -> 4757315.5 | H16: =H10+H14 -> 4373698 | I16: =I10+I14 -> 3992346 | ... AK16: =AK10+AK14 -> 5312271.9
A18: Balance Check | B18: =ROUND(B7-B16,2) -> 0 | C18: =ROUND(C7-C16,2) -> 0 | D18: =ROUND(D7-D16,2) -> 0 | E18: =ROUND(E7-E16,2) -> 0 | F18: =ROUND(F7-F16,2) -> 0 | G18: =ROUND(G7-G16,2) -> 0 | H18: =ROUND(H7-H16,2) -> 0 | I18: =ROUND(I7-I16,2) -> 0 | ... AK18: =ROUND(AK7-AK16,2) -> 0
